inquirer2/__init__.py
inquirer2/color_print.py
inquirer2/prompt.py
inquirer2/separator.py
inquirer2/utils.py
inquirer2/prompts/__init__.py
inquirer2/prompts/checkbox.py
inquirer2/prompts/common.py
inquirer2/prompts/confirm.py
inquirer2/prompts/editor.py
inquirer2/prompts/expand.py
inquirer2/prompts/input.py
inquirer2/prompts/list.py
inquirer2/prompts/password.py
inquirer2/prompts/rawlist.py
inquirer2-1.0.0.dist-info/LICENSE
inquirer2-1.0.0.dist-info/METADATA
inquirer2-1.0.0.dist-info/WHEEL
inquirer2-1.0.0.dist-info/top_level.txt
inquirer2-1.0.0.dist-info/RECORD
